{"1":{"total_words":1,"words":["كٓهيعٓصٓ"]},"2":{"total_words":5,"words":["ذِكرُ","رَحمَتِ","رَبِّكَ","عَبدَهٗ","زَكَرِيَّا"]},"3":{"total_words":5,"words":["اِذ","نَادى","رَبَّهٗ","نِدَآءً","خَفِيًّا"]},"4":{"total_words":14,"words":["قَالَ","رَبِّ","اِنِّى","وَهَنَ","العَظمُ","مِنِّى","وَاشتَعَلَ","الرَّاسُ","شَيبًا","وَّلَم","اَكُن","بِدُعَآٮِٕكَ","رَبِّ","شَقِيًّا"]},"5":{"total_words":13,"words":["وَاِنِّى","خِفتُ","المَوَالِىَ","مِن","وَّرَآءِى","وَكَانَتِ","امرَاَتِى","عَاقِرًا","فَهَب","لِى","مِن","لَّدُنكَ","وَلِيًّا"]},"6":{"total_words":9,"words":["يَّرِثُنِى","وَيَرِثُ","مِن","الِ","يَعقُوبَ","وَاجعَلهُ","رَبِّ","رَضِيًّا"]},"7":{"total_words":12,"words":["يزَكَرِيَّا","اِنَّا","نُبَشِّرُكَ","بِغُلم","اسمُهٗ","يَحيى","لَم","نَجعَل","لَّهٗ","مِن","قَبلُ","سَمِيًّا"]},"8":{"total_words":14,"words":["قَالَ","رَبِّ","اَنّى","يَكُونُ","لِى","غُلمٌ","وَّكَانَتِ","امرَاَتِى","عَاقِرًا","وَّقَد","بَلَغتُ","مِنَ","الكِبَرِ","عِتِيًّا"]},"9":{"total_words":14,"words":["قَالَ","كَذلِكَ","قَالَ","رَبُّكَ","هُوَ","عَلَىَّ","هَيِّنٌ","وَّقَد","خَلَقتُكَ","مِن","قَبلُ","وَلَم","تَكُ","شَئًا"]},"10":{"total_words":14,"words":["قَالَ","رَبِّ","اجعَل","لِّى","ايَةً ؕ","قَالَ","ايَتُكَ","اَلَّا","تُكَلِّمَ","النَّاسَ","ثَلثَ","لَيَالٍ","سَوِيًّا"]},"11":{"total_words":11,"words":["فَخَرَجَ","عَلى","قَومِهٖ","مِنَ","المِحرَابِ","فَاَوحٓى","اِلَيهِم","اَن","سَبِّحُوا","بُكرَةً","وَّعَشِيًّا"]},"12":{"total_words":8,"words":["ييَحيى","خُذِ","الكِتبَ","بِقُوَّةٍؕ","وَاتَينهُ","الحُكمَ","صَبِيًّا"]},"13":{"total_words":7,"words":["وَّحَنَانًا","مِّن","لَّدُنَّا","وَزَكوةً ؕ","وَّكَانَ","تَقِيًّا"]},"14":{"total_words":6,"words":["وَّبَرًّا","بِوَالِدَيهِ","وَلَم","يَكُن","جَبَّارًا","عَصِيًّا"]},"15":{"total_words":9,"words":["وَسَلمٌ","عَلَيهِ","يَومَ","وُلِدَ","وَيَومَ","يَمُوتُ","وَيَومَ","يُبعَثُ","حَيًّا"]},"16":{"total_words":10,"words":["وَاذكُر","فِى","الكِتبِ","مَريَمَ","اِذِ","انتَبَذَت","مِن","اَهلِهَا","مَكَانًا","شَرقِيًّا"]},"17":{"total_words":11,"words":["فَاتَّخَذَت","مِن","دُونِهِم","حِجَابًا","فَاَرسَلنَا","اِلَيهَا","رُوحَنَا","فَتَمَثَّلَ","لَهَا","بَشَرًا","سَوِيًّا"]},"18":{"total_words":8,"words":["قَالَت","اِنِّى","اَعُوذُ","بِالرَّحمنِ","مِنكَ","اِن","كُنتَ","تَقِيًّا"]},"19":{"total_words":9,"words":["قَالَ","اِنَّمَا","اَنَا","رَسُولُ","رَبِّكِ","لِاَهَبَ","لَكِ","غُلمًا","زَكِيًّا"]},"20":{"total_words":11,"words":["قَالَت","اَنّى","يَكُونُ","لِى","غُلمٌ","وَّلَم","يَمسَسنِى","بَشَرٌ","وَّلَم","اَكُ","بَغِيًّا"]},"21":{"total_words":17,"words":["قَالَ","كَذلِكِ","قَالَ","رَبُّكِ","هُوَ","عَلَىَّ","هَيِّنٌ","وَلِنَجعَلَهٗ","ايَةً","لِّلنَّاسِ","وَرَحمَةً","مِّنَّا","وَكَانَ","اَمرًا","مَّقضِيًّا"]},"22":{"total_words":6,"words":["فَحَمَلَتهُ","فَانتَبَذَت","بِهٖ","مَكَانًا","قَصِيًّا"]},"23":{"total_words":13,"words":["فَاَجَآءَهَا","المَخَاضُ","اِلى","جِذعِ","النَّخلَةِ","قَالَت","يلَيتَنِى","مِتُّ","قَبلَ","هذَا","وَكُنتُ","نَسيًا","مَّنسِيًّا"]},"24":{"total_words":10,"words":["فَنَادٮهَا","مِن","تَحتِهَا","اَلَّا","تَحزَنِى","قَد","جَعَلَ","رَبُّكِ","تَحتَكِ","سَرِيًّا"]},"25":{"total_words":8,"words":["وَهُزِّى","اِلَيكِ","بِجِذعِ","النَّخلَةِ","تُسقِط","عَلَيكِ","رُطَبًا","جَنِيًّا"]},"26":{"total_words":19,"words":["فَكُلِى","وَاشرَبِى","وَقَرِّى","عَينًا","فَاِمَّا","تَرَيِنَّ","مِنَ","البَشَرِ","اَحَدًا","فَقُولِى","اِنِّى","نَذَرتُ","لِلرَّحمنِ","صَومًا","فَلَن","اُكَلِّمَ","اليَومَ","اِنسِيًّا"]},"27":{"total_words":11,"words":["فَاَتَت","بِهٖ","قَومَهَا","تَحمِلُهٗؕ","قَالُوا","يمَريَمُ","لَقَد","جِئتِ","شَئًا","فَرِيًّا"]},"28":{"total_words":11,"words":["ياُختَ","هرُونَ","مَا","كَانَ","اَ بُوكِ","امرَاَ","سَوءٍ","وَّمَا","كَانَت","اُمُّكِ","بَغِيًّا"]},"29":{"total_words":11,"words":["فَاَشَارَت","اِلَيهِ ؕ","قَالُوا","كَيفَ","نُكَلِّمُ","مَن","كَانَ","فِى","المَهدِ","صَبِيًّا"]},"30":{"total_words":8,"words":["قَالَ","اِنِّى","عَبدُ","اللّهِ ؕ","اتٮنِىَ","الكِتبَ","وَجَعَلَنِى","نَبِيًّا"]},"31":{"total_words":11,"words":["وَّجَعَلَنِى","مُبرَكًا","اَينَ","مَا","كُنتُ","وَاَوصنِى","بِالصَّلوةِ","وَالزَّكوةِ","مَا","دُمتُ","حَيًّا"]},"32":{"total_words":6,"words":["وَّبَرًّا","بِوَالِدَتِى","وَلَم","يَجعَلنِى","جَبَّارًا","شَقِيًّا"]},"33":{"total_words":9,"words":["وَالسَّلمُ","عَلَىَّ","يَومَ","وُلِدتُّ","وَيَومَ","اَمُوتُ","وَيَومَ","اُبعَثُ","حَيًّا"]},"34":{"total_words":10,"words":["ذ لِكَ","عِيسَى","ابنُ","مَريَمَ","قَولَ","الحَقِّ","الَّذِى","فِيهِ","يَمتَرُونَ"]},"35":{"total_words":18,"words":["مَا","كَانَ","لِلّهِ","اَن","يَّتَّخِذَ","مِن","وَّلَدٍ","سُبحنَهٗؕ","اِذَا","قَضٓى","اَمرًا","فَاِنَّمَا","يَقُولُ","لَهٗ","كُن","فَيَكُونُؕ"]},"36":{"total_words":9,"words":["وَاِنَّ","اللّهَ","رَبِّى","وَرَبُّكُم","فَاعبُدُوهُ ؕ","هذَا","صِرَاطٌ","مُّستَقِيمٌ"]},"37":{"total_words":12,"words":["فَاختَلَفَ","الاَحزَابُ","مِن","بَينِهِم","فَوَيلٌ","لِّلَّذِينَ","كَفَرُوا","مِن","مَّشهَدِ","يَومٍ","عَظِيمٍ"]},"38":{"total_words":12,"words":["اَسمِع","بِهِم","وَاَبصِر","يَومَ","يَاتُونَنَا","لكِنِ","الظّلِمُونَ","اليَومَ","فِى","ضَللٍ","مُّبِينٍ"]},"39":{"total_words":12,"words":["وَاَنذِرهُم","يَومَ","الحَسرَةِ","اِذ","قُضِىَ","الاَمرُ","وَهُم","فِى","غَفلَةٍ","وَّهُم","لَا","يُؤمِنُونَ"]},"40":{"total_words":8,"words":["اِنَّا","نَحنُ","نَرِثُ","الاَرضَ","وَمَن","عَلَيهَا","وَاِلَينَا","يُرجَعُونَ"]},"41":{"total_words":9,"words":["وَاذكُر","فِى","الكِتبِ","اِبرهِيمَ","اِنَّهٗ","كَانَ","صِدِّيقًا","نَّبِيًّا"]},"42":{"total_words":15,"words":["اِذ","قَالَ","لِاَبِيهِ","ياَبَتِ","لِمَ","تَعبُدُ","مَا","لَا","يَسمَعُ","وَلَا","يُبصِرُ","وَ لَا","يُغنِى","عَنكَ","شَئًا"]},"43":{"total_words":13,"words":["ياَبَتِ","اِنِّى","قَد","جَآءَنِى","مِنَ","العِلمِ","مَا","لَم","يَاتِكَ","فَاتَّبِعنِى","اَهدِكَ","صِرَاطًا","سَوِيًّا"]},"44":{"total_words":10,"words":["ياَبَتِ","لَا","تَعبُدِ","الشَّيطنَ ؕ","اِنَّ","الشَّيطنَ","كَانَ","لِلرَّحمنِ","عَصِيًّا"]},"45":{"total_words":11,"words":["ياَبَتِ","اِنِّى","اَخَافُ","اَن","يَّمَسَّكَ","عَذَابٌ","مِّنَ","الرَّحمنِ","فَتَكُونَ","لِلشَّيطنِ","وَلِيًّا"]},"46":{"total_words":14,"words":["قَالَ","اَرَاغِبٌ","اَنتَ","عَن","الِهَتِى","ياِبرهِيمُ","لَٮِٕن","لَّم","تَنتَهِ","لَاَرجُمَنَّكَ","وَاهجُرنِى","مَلِيًّا"]},"47":{"total_words":12,"words":["قَالَ","سَلمٌ","عَلَيكَ","سَاَستَغفِرُ","لَكَ","رَبِّىؕ","اِنَّهٗ","كَانَ","بِى","حَفِيًّا"]},"48":{"total_words":14,"words":["وَ اَعتَزِلُكُم","وَمَا","تَدعُونَ","مِن","دُونِ","اللّهِ","وَاَدعُوا","رَبِّى","عَسٓى","اَلَّا","اَكُونَ","بِدُعَآءِ","رَبِّى","شَقِيًّا"]},"49":{"total_words":15,"words":["فَلَمَّا","اعتَزَلَهُم","وَمَا","يَعبُدُونَ","مِن","دُونِ","اللّهِ","وَهَبنَا","لَهٗ","اِسحقَ","وَيَعقُوبَ ؕ","وَكُلًّا","جَعَلنَا","نَبِيًّا"]},"50":{"total_words":9,"words":["وَوَهَبنَا","لَهُم","مِّن","رَّحمَتِنَا","وَجَعَلنَا","لَهُم","لِسَانَ","صِدقٍ","عَلِيًّا"]},"51":{"total_words":11,"words":["وَاذكُر","فِى","الكِتبِ","مُوسٓى","اِنَّهٗ","كَانَ","مُخلَصًا","وَّكَانَ","رَسُولًا","نَّبِيًّا"]},"52":{"total_words":7,"words":["وَنَادَينهُ","مِن","جَانِبِ","الطُّورِ","الاَيمَنِ","وَقَرَّبنهُ","نَجِيًّا"]},"53":{"total_words":7,"words":["وَ وَهَبنَا","لَهٗ","مِن","رَّحمَتِنَا","اَخَاهُ","هرُونَ","نَبِيًّا"]},"54":{"total_words":12,"words":["وَاذكُر","فِى","الكِتبِ","اِسمعِيلَ","اِنَّهٗ","كَانَ","صَادِقَ","الوَعدِ","وَكَانَ","رَسُولًا","نَّبِيًّا"]},"55":{"total_words":9,"words":["وَ كَانَ","يَامُرُ","اَهلَهٗ","بِالصَّلوةِ","وَالزَّكوةِ","وَكَانَ","عِندَ","رَبِّهٖ","مَرضِيًّا"]},"56":{"total_words":9,"words":["وَاذكُر","فِى","الكِتبِ","اِدرِيسَ","اِنَّهٗ","كَانَ","صِدِّيقًا","نَّبِيًّا"]},"57":{"total_words":3,"words":["وَّرَفَعنهُ","مَكَانًا","عَلِيًّا"]},"58":{"total_words":31,"words":["اُولٓٮِٕكَ","الَّذِينَ","اَنعَمَ","اللّهُ","عَلَيهِم","مِّنَ","النَّبِيّٖنَ","مِن","ذُرِّيَّةِ","ادَمَ","وَمِمَّن","حَمَلنَا","مَعَ","نُوحٍ","وَّمِن","ذُرِّيَّةِ","اِبرهِيمَ","وَاِسرَآءِيلَ","وَمِمَّن","هَدَينَا","وَاجتَبَينَا ؕ","اِذَا","تُتلى","عَلَيهِم","ايتُ","الرَّحمنِ","خَرُّوا","سُجَّدًا","وَّبُكِيًّا"]},"59":{"total_words":13,"words":["فَخَلَفَ","مِن","بَعدِهِم","خَلفٌ","اَضَاعُوا","الصَّلوةَ","وَاتَّبَعُوا","الشَّهَوتِ","فَسَوفَ","يَلقَونَ","غَيًّا"]},"60":{"total_words":12,"words":["اِلَّا","مَن","تَابَ","وَامَنَ","وَعَمِلَ","صَالِحًا","فَاُولٓٮِٕكَ","يَدخُلُونَ","الجَنَّةَ","وَلَا","يُظلَمُونَ","شَئًا"]},"61":{"total_words":12,"words":["جَنّتِ","عَدنٍ","الَّتِى","وَعَدَ","الرَّحمنُ","عِبَادَهٗ","بِالغَيبِ ؕ","اِنَّهٗ","كَانَ","وَعدُهٗ","مَاتِيًّا"]},"62":{"total_words":12,"words":["لَّا","يَسمَعُونَ","فِيهَا","لَغوًا","اِلَّا","سَلمًاؕ","وَلَهُم","رِزقُهُم","فِيهَا","بُكرَةً","وَّعَشِيًّا"]},"63":{"total_words":9,"words":["تِلكَ","الجَنَّةُ","الَّتِى","نُورِثُ","مِن","عِبَادِنَا","مَن","كَانَ","تَقِيًّا"]},"64":{"total_words":20,"words":["وَمَا","نَتَنَزَّلُ","اِلَّا","بِاَمرِ","رَبِّكَ","لَهٗ","مَا","بَينَ","اَيدِينَا","وَمَا","خَلفَنَا","وَمَا","بَينَ","ذ لِكَ","وَمَا","كَانَ","رَبُّكَ","نَسِيًّا"]},"65":{"total_words":13,"words":["رَّبُّ","السَّموتِ","وَ الاَرضِ","وَمَا","بَينَهُمَا","فَاعبُدهُ","وَاصطَبِر","لِعِبَادَتِهٖؕ","هَل","تَعلَمُ","لَهٗ","سَمِيًّا"]},"66":{"total_words":8,"words":["وَيَقُولُ","الاِنسَانُ","ءَاِذَا","مَا","مِتُّ","لَسَوفَ","اُخرَجُ","حَيًّا"]},"67":{"total_words":10,"words":["اَوَلَا","يَذكُرُ","الاِنسَانُ","اَنَّا","خَلَقنهُ","مِن","قَبلُ","وَلَم","يَكُ","شَئًا"]},"68":{"total_words":8,"words":["فَوَرَبِّكَ","لَنَحشُرَنَّهُم","وَالشَّيطِينَ","ثُمَّ","لَنُحضِرَنَّهُم","حَولَ","جَهَنَّمَ","جِثِيًّا"]},"69":{"total_words":10,"words":["ثُمَّ","لَنَنزِعَنَّ","مِن","كُلِّ","شِيعَةٍ","اَيُّهُم","اَشَدُّ","عَلَى","الرَّحمنِ","عِتِيًّا"]},"70":{"total_words":8,"words":["ثُمَّ","لَنَحنُ","اَعلَمُ","بِالَّذِينَ","هُم","اَولى","بِهَا","صِلِيًّا"]},"71":{"total_words":10,"words":["وَاِن","مِّنکُم","اِلَّا","وَارِدُهَا ؕ","كَانَ","عَلى","رَبِّكَ","حَتمًا","مَّقضِيًّا"]},"72":{"total_words":8,"words":["ثُمَّ","نُنَجِّى","الَّذِينَ","اتَّقَوا","وَّنَذَرُ","الظّلِمِينَ","فِيهَا","جِثِيًّا"]},"73":{"total_words":16,"words":["وَاِذَا","تُتلى","عَلَيهِم","ايتُنَا","بَيِّنتٍ","قَالَ","الَّذِينَ","كَفَرُوا","لِلَّذِينَ","امَنُوا","اَىُّ","الفَرِيقَينِ","خَيرٌ","مَّقَامًا","وَّاَحسَنُ","نَدِيًّا"]},"74":{"total_words":9,"words":["وَكَم","اَهلَكنَا","قَبلَهُم","مِّن","قَرنٍ","هُم","اَحسَنُ","اَثَاثًا","وَّرِءيًا"]},"75":{"total_words":26,"words":["قُل","مَن","كَانَ","فِى","الضَّللَةِ","فَليَمدُد","لَهُ","الرَّحمنُ","مَدًّا","حَتّٓى","اِذَا","رَاَوا","مَا","يُوعَدُونَ","اِمَّا","العَذَابَ","وَاِمَّا","السَّاعَةَ ؕ","فَسَيَعلَمُونَ","مَن","هُوَ","شَرٌّ","مَّكَانًا","وَّاَضعَفُ","جُندًا"]},"76":{"total_words":14,"words":["وَيَزِيدُ","اللّهُ","الَّذِينَ","اهتَدَوا","هُدًىؕ","وَالبقِيتُ","الصّلِحتُ","خَيرٌ","عِندَ","رَبِّكَ","ثَوَابًا","وَّخَيرٌ","مَّرَدًّا"]},"77":{"total_words":8,"words":["اَفَرَءَيتَ","الَّذِى","كَفَرَ","بِايتِنَا","وَقَالَ","لَاُوتَيَنَّ","مَالًا","وَّوَلَدًا ؕ"]},"78":{"total_words":7,"words":["اَطَّلَعَ","الغَيبَ","اَمِ","اتَّخَذَ","عِندَ","الرَّحمنِ","عَهدًا"]},"79":{"total_words":10,"words":["كَلَّا  ؕ","سَنَكتُبُ","مَا","يَقُولُ","وَنَمُدُّ","لَهٗ","مِنَ","العَذَابِ","مَدًّا"]},"80":{"total_words":5,"words":["وَّنَرِثُهٗ","مَا","يَقُولُ","وَيَاتِينَا","فَردًا"]},"81":{"total_words":8,"words":["وَاتَّخَذُوا","مِن","دُونِ","اللّهِ","الِهَةً","لِّيَكُونُوا","لَهُم","عِزًّا"]},"82":{"total_words":7,"words":["كَلَّا ؕ","سَيَكفُرُونَ","بِعِبَادَتِهِم","وَيَكُونُونَ","عَلَيهِم","ضِدًّا"]},"83":{"total_words":9,"words":["اَلَم","تَرَ","اَنَّا","اَرسَلنَا","الشَّيطِينَ","عَلَى","الكفِرِينَ","تَؤُزُّهُم","اَزًّا"]},"84":{"total_words":8,"words":["فَلَا","تَعجَل","عَلَيهِم ؕ","اِنَّمَا","نَعُدُّ","لَهُم","عَدًّا"]},"85":{"total_words":6,"words":["يَومَ","نَحشُرُ","المُتَّقِينَ","اِلَى","الرَّحمنِ","وَفدًا"]},"86":{"total_words":5,"words":["وَّنَسُوقُ","المُجرِمِينَ","اِلى","جَهَنَّمَ","وِردًا"]},"87":{"total_words":9,"words":["لَا","يَملِكُونَ","الشَّفَاعَةَ","اِلَّا","مَنِ","اتَّخَذَ","عِندَ","الرَّحمنِ","عَهدًا"]},"88":{"total_words":4,"words":["وَقَالُوا","اتَّخَذَ","الرَّحمنُ","وَلَدًا ؕ"]},"89":{"total_words":4,"words":["لَقَد","جِئتُم","شَئًا","اِدًّا"]},"90":{"total_words":9,"words":["تَكَادُ","السَّموتُ","يَتَفَطَّرنَ","مِنهُ","وَتَنشَقُّ","الاَرضُ","وَتَخِرُّ","الجِبَالُ","هَدًّا"]},"91":{"total_words":4,"words":["اَن","دَعَوا","لِلرَّحمنِ","وَلَدًا"]},"92":{"total_words":6,"words":["وَمَا","يَنبَغِى","لِلرَّحمنِ","اَن","يَّتَّخِذَ","وَلَدًا ؕ"]},"93":{"total_words":10,"words":["اِن","كُلُّ","مَن","فِى","السَّموتِ","وَالاَرضِ","اِلَّا","اتِى","الرَّحمنِ","عَبدًا ؕ"]},"94":{"total_words":4,"words":["لَقَد","اَحصٮهُم","وَعَدَّهُم","عَدًّا"]},"95":{"total_words":5,"words":["وَكُلُّهُم","اتِيهِ","يَومَ","القِيمَةِ","فَردًا"]},"96":{"total_words":9,"words":["اِنَّ","الَّذِينَ","امَنُوا","وَعَمِلُوا","الصّلِحتِ","سَيَجعَلُ","لَهُمُ","الرَّحمنُ","وُدًّا"]},"97":{"total_words":10,"words":["فَاِنَّمَا","يَسَّرنهُ","بِلِسَانِكَ","لِتُبَشِّرَ","بِهِ","المُتَّقِينَ","وَتُنذِرَ","بِهٖ","قَومًا","لُّدًّا"]},"98":{"total_words":14,"words":["وَكَم","اَهلَكنَا","قَبلَهُم","مِّن","قَرنٍؕ","هَل","تُحِسُّ","مِنهُم","مِّن","اَحَدٍ","اَو","تَسمَعُ","لَهُم","رِكزًا"]}}