{"1":{"total_words":1,"words":["حمٓ"]},"2":{"total_words":2,"words":["وَالكِتبِ","المُبِينِ"]},"3":{"total_words":6,"words":["اِنَّا","جَعَلنهُ","قُرءنًا","عَرَبِيًّا","لَّعَلَّكُم","تَعقِلُونَ"]},"4":{"total_words":7,"words":["وَاِنَّهٗ","فِى","اُمِّ","الكِتبِ","لَدَينَا","لَعَلِىٌّ","حَكِيمٌؕ"]},"5":{"total_words":8,"words":["اَفَنَضرِبُ","عَنكُمُ","الذِّكرَ","صَفحًا","اَن","كُنتُم","قَومًا","مُّسرِفِينَ"]},"6":{"total_words":6,"words":["وَكَم","اَرسَلنَا","مِن","نَّبِىٍّ","فِى","الاَوَّلِينَ"]},"7":{"total_words":8,"words":["وَمَا","يَاتِيهِم","مِّن","نَّبِىٍّ","اِلَّا","كَانُوا","بِهٖ","يَستَهزِءُونَ"]},"8":{"total_words":7,"words":["فَاَهلَكنَا","اَشَدَّ","مِنهُم","بَطشًا","وَّمَضى","مَثَلُ","الاَوَّلِينَ"]},"9":{"total_words":10,"words":["وَلَٮِٕن","سَاَلتَهُم","مَّن","خَلَقَ","السَّموتِ","وَالاَرضَ","لَيَقُولُنَّ","خَلَقَهُنَّ","العَزِيزُ","العَلِيمُ"]},"10":{"total_words":11,"words":["الَّذِى","جَعَلَ","لَكُمُ","الاَرضَ","مَهدًا","وَّ جَعَلَ","لَكُم","فِيهَا","سُبُلًا","لَّعَلَّكُم","تَهتَدُونَ"]},"11":{"total_words":13,"words":["وَالَّذِى","نَزَّلَ","مِنَ","السَّمَآءِ","مَآءً","بِقَدَرٍ","فَاَنشَرنَا","بِهٖ","بَلدَةً","مَّيتًا","كَذلِكَ","تُخرَجُونَ"]},"12":{"total_words":11,"words":["وَالَّذِى","خَلَقَ","الاَزوَاجَ","كُلَّهَا","وَجَعَلَ","لَكُم","مِّنَ","الفُلكِ","وَالاَنعَامِ","مَا","تَركَبُونَ"]},"13":{"total_words":20,"words":["لِتَستَوٗا","عَلى","ظُهُورِهٖ","ثُمَّ","تَذكُرُوا","نِعمَةَ","رَبِّكُم","اِذَا","استَوَيتُم","عَلَيهِ","وَتَقُولُوا","سُبحنَ","الَّذِى","سَخَّرَ","لَنَا","هذَا","وَمَا","كُنَّا","لَهٗ","مُقرِنِينَ"]},"14":{"total_words":4,"words":["وَاِنَّا","اِلى","رَبِّنَا","لَمُنقَلِبُونَ"]},"15":{"total_words":10,"words":["وَجَعَلُوا","لَهٗ","مِن","عِبَادِهٖ","جُزءًا ؕ","اِنَّ","الاِنسَانَ","لَكَفُورٌ","مُّبِينٌؕ"]},"16":{"total_words":7,"words":["اَمِ","اتَّخَذَ","مِمَّا","يَخلُقُ","بَنتٍ","وَّاَصفٮكُم","بِالبَنِينَ"]},"17":{"total_words":12,"words":["وَاِذَا","بُشِّرَ","اَحَدُهُم","بِمَا","ضَرَبَ","لِلرَّحمنِ","مَثَلًا","ظَلَّ","وَجهُهٗ","مُسوَدًّا","وَّهُوَ","كَظِيمٌ"]},"18":{"total_words":9,"words":["اَوَمَن","يُّنَشَّؤُا","فِى","الحِليَةِ","وَهُوَ","فِى","الخِصَامِ","غَيرُ","مُبِينٍ"]},"19":{"total_words":14,"words":["وَجَعَلُوا","المَلٓٮِٕكَةَ","الَّذِينَ","هُم","عِبَادُ","الرَّحمنِ","اِنَاثًا ؕ","اَشَهِدُوا","خَلقَهُم ؕ","سَتُكتَبُ","شَهَادَتُهُم","وَيُسَٔلُونَ"]},"20":{"total_words":17,"words":["وَقَالُوا","لَو","شَآءَ","الرَّحمنُ","مَا","عَبَدنهُمؕ","مَا","لَهُم","بِذلِكَ","مِن","عِلمٍ","اِن","هُم","اِلَّا","يَخرُصُونَؕ"]},"21":{"total_words":8,"words":["اَم","اتَينهُم","كِتبًا","مِّن","قَبلِهٖ","فَهُم","بِهٖ","مُستَمسِكُونَ"]},"22":{"total_words":11,"words":["بَل","قَالُوا","اِنَّا","وَجَدنَا","ابَآءَنَا","عَلٓى","اُمَّةٍ","وَّاِنَّا","عَلٓى","اثرِهِم","مُّهتَدُونَ"]},"23":{"total_words":21,"words":["وَكَذلِكَ","مَا","اَرسَلنَا","مِن","قَبلِكَ","فِى","قَريَةٍ","مِّن","نَّذِيرٍ","اِلَّا","قَالَ","مُترَفُوهَا","اِنَّا","وَجَدنَا","ابَآءَنَا","عَلٓى","اُمَّةٍ","وَّاِنَّا","عَلٓى","اثرِهِم","مُّقتَدُونَ"]},"24":{"total_words":16,"words":["قلَ","اَوَلَو","جِئتُكُم","بِاَهدى","مِمَّا","وَجَدتُّم","عَلَيهِ","ابَآءَكُم ؕ","قَالُوا","اِنَّا","بِمَا","اُرسِلتُم","بِهٖ","كفِرُونَ"]},"25":{"total_words":8,"words":["فَانتَقَمنَا","مِنهُم","فَانظُر","كَيفَ","كَانَ","عَاقِبَةُ","المُكَذِّبِينَ"]},"26":{"total_words":9,"words":["وَاِذ","قَالَ","اِبرهِيمُ","لِاَبِيهِ","وَقَومِهٖ","اِنَّنِى","بَرَآءٌ","مِّمَّا","تَعبُدُونَ"]},"27":{"total_words":5,"words":["اِلَّا","الَّذِى","فَطَرَنِى","فَاِنَّهٗ","سَيَهدِينِ"]},"28":{"total_words":7,"words":["وَ جَعَلَهَا","كَلِمَةً","بَاقِيَةً","فِى","عَقِبِهٖ","لَعَلَّهُم","يَرجِعُونَ"]},"29":{"total_words":9,"words":["بَل","مَتَّعتُ","هٓؤُلَاءِ","وَابَآءَهُم","حَتّى","جَآءَهُمُ","الحَقُّ","وَرَسُولٌ","مُّبِينٌ"]},"30":{"total_words":9,"words":["وَلَمَّا","جَآءَهُمُ","الحَقُّ","قَالُوا","هذَا","سِحرٌ","وَّاِنَّا","بِهٖ","كفِرُونَ"]},"31":{"total_words":10,"words":["وَقَالُوا","لَولَا","نُزِّلَ","هذَا","القُرانُ","عَلى","رَجُلٍ","مِّنَ","القَريَتَينِ","عَظِيمٍ"]},"32":{"total_words":28,"words":["اَهُم","يَقسِمُونَ","رَحمَتَ","رَبِّكَ ؕ","نَحنُ","قَسَمنَا","بَينَهُم","مَّعِيشَتَهُم","فِى","الحَيوةِ","الدُّنيَا","وَرَفَعنَا","بَعضَهُم","فَوقَ","بَعضٍ","دَرَجتٍ","لِّيَتَّخِذَ","بَعضُهُم","بَعضًا","سُخرِيًّا ؕ","وَرَحمَتُ","رَبِّكَ","خَيرٌ","مِّمَّا","يَجمَعُونَ"]},"33":{"total_words":17,"words":["وَلَولَا","اَن","يَّكُونَ","النَّاسُ","اُمَّةً","وَّاحِدَةً","لَّجَعَلنَا","لِمَن","يَّكفُرُ","بِالرَّحمنِ","لِبُيُوتِهِم","سُقُفًا","مِّن","فِضَّةٍ","وَّمَعَارِجَ","عَلَيهَا","يَظهَرُونَ"]},"34":{"total_words":5,"words":["وَلِبُيُوتِهِم","اَبوَابًا","وَّسُرُرًا","عَلَيهَا","يَتَّكُِٔونَ"]},"35":{"total_words":14,"words":["وَزُخرُفًا ؕ","وَاِن","كُلُّ","ذ لِكَ","لَمَّا","مَتَاعُ","الحَيوةِ","الدُّنيَا ؕ","وَالاخِرَةُ","عِندَ","رَبِّكَ","لِلمُتَّقِينَ"]},"36":{"total_words":11,"words":["وَمَن","يَّعشُ","عَن","ذِكرِ","الرَّحمنِ","نُقَيِّض","لَهٗ","شَيطنًا","فَهُوَ","لَهٗ","قَرِينٌ"]},"37":{"total_words":7,"words":["وَاِنَّهُم","لَيَصُدُّونَهُم","عَنِ","السَّبِيلِ","وَيَحسَبُونَ","اَنَّهُم","مُّهتَدُونَ"]},"38":{"total_words":11,"words":["حَتّٓى","اِذَا","جَآءَنَا","قَالَ","يلَيتَ","بَينِى","وَبَينَكَ","بُعدَ","المَشرِقَينِ","فَبِئسَ","القَرِينُ"]},"39":{"total_words":9,"words":["وَلَن","يَّنفَعَكُمُ","اليَومَ","اِذ","ظَّلَمتُم","اَنَّكُم","فِى","العَذَابِ","مُشتَرِكُونَ"]},"40":{"total_words":11,"words":["اَفَاَنتَ","تُسمِعُ","الصُّمَّ","اَو","تَهدِى","العُمىَ","وَمَن","كَانَ","فِى","ضَللٍ","مُّبِينٍ"]},"41":{"total_words":6,"words":["فَاِمَّا","نَذهَبَنَّ","بِكَ","فَاِنَّا","مِنهُم","مُّنتَقِمُونَ"]},"42":{"total_words":7,"words":["اَو","نُرِيَنَّكَ","الَّذِى","وَعَدنهُم","فَاِنَّا","عَلَيهِم","مُّقتَدِرُونَ"]},"43":{"total_words":9,"words":["فَاستَمسِك","بِالَّذِى","اُوحِىَ","اِلَيكَ","اِنَّكَ","عَلى","صِرَاطٍ","مُّستَقِيمٍ"]},"44":{"total_words":7,"words":["وَاِنَّهٗ","لَذِكرٌ","لَّكَ","وَلِقَومِكَ","وَسَوفَ","تُسَٔلُونَ"]},"45":{"total_words":13,"words":["وَسَٔل","مَن","اَرسَلنَا","مِن","قَبلِكَ","مِن","رُّسُلِنَا","اَجَعَلنَا","مِن","دُونِ","الرَّحمنِ","الِهَةً","يُّعبَدُونَ"]},"46":{"total_words":12,"words":["وَلَقَد","اَرسَلنَا","مُوسى","بِايتِنَا","اِلى","فِرعَونَ","وَمَلَاٮِٕه","فَقَالَ","اِنِّى","رَسُولُ","رَبِّ","العلَمِينَ"]},"47":{"total_words":7,"words":["فَلَمَّا","جَآءَهُم","بِايتِنَا","اِذَا","هُم","مِّنهَا","يَضحَكُونَ"]},"48":{"total_words":14,"words":["وَمَا","نُرِيهِم","مِّن","ايَةٍ","اِلَّا","هِىَ","اَكبَرُ","مِن","اُختِهَا","وَ اَخَذنهُم","بِالعَذَابِ","لَعَلَّهُم","يَرجِعُونَ"]},"49":{"total_words":11,"words":["وَقَالُوا","ياَيُّهَ","السَّاحِرُ","ادعُ","لَنَا","رَبَّكَ","بِمَا","عَهِدَ","عِندَكَ","اِنَّنَا","لَمُهتَدُونَ"]},"50":{"total_words":7,"words":["فَلَمَّا","كَشَفنَا","عَنهُمُ","العَذَابَ","اِذَا","هُم","يَنكُثُونَ"]},"51":{"total_words":18,"words":["وَنَادى","فِرعَونُ","فِى","قَومِهٖ","قَالَ","يقَومِ","اَلَيسَ","لِى","مُلكُ","مِصرَ","وَهذِهِ","الاَنهرُ","تَجرِى","مِن","تَحتِى","اَفَلَا","تُبصِرُونَؕ"]},"52":{"total_words":11,"words":["اَم","اَنَا","خَيرٌ","مِّن","هذَا","الَّذِى","هُوَ","مَهِينٌ","وَّلَا","يَكَادُ","يُبِينُ"]},"53":{"total_words":11,"words":["فَلَولَا","اُلقِىَ","عَلَيهِ","اَسوِرَةٌ","مِّن","ذَهَبٍ","اَو","جَآءَ","مَعَهُ","المَلٓٮِٕكَةُ","مُقتَرِنِينَ"]},"54":{"total_words":8,"words":["فَاستَخَفَّ","قَومَهٗ","فَاَطَاعُوهُؕ","اِنَّهُم","كَانُوا","قَومًا","فسِقِينَ"]},"55":{"total_words":6,"words":["فَلَمَّا","اسَفُونَا","انتَقَمنَا","مِنهُم","فَاَغرَقنهُم","اَجمَعِينَ"]},"56":{"total_words":4,"words":["فَجَعَلنهُم","سَلَفًا","وَّمَثَلًا","لِّلاخِرِينَ"]},"57":{"total_words":10,"words":["وَلَمَّا","ضُرِبَ","ابنُ","مَريَمَ","مَثَلًا","اِذَا","قَومُكَ","مِنهُ","يَصِدُّونَ"]},"58":{"total_words":16,"words":["وَقَالُوٓا","ءَالِهَتُنَا","خَيرٌ","اَم","هُوَؕ","مَا","ضَرَبُوهُ","لَكَ","اِلَّا","جَدَلًا ؕ","بَل","هُم","قَومٌ","خَصِمُونَ"]},"59":{"total_words":10,"words":["اِن","هُوَ","اِلَّا","عَبدٌ","اَنعَمنَا","عَلَيهِ","وَجَعَلنهُ","مَثَلًا","لِّبَنِى","اِسرَآءِيلَؕ"]},"60":{"total_words":8,"words":["وَلَو","نَشَآءُ","لَجَعَلنَا","مِنكُم","مَّلٓٮِٕكَةً","فِى","الاَرضِ","يَخلُفُونَ"]},"61":{"total_words":11,"words":["وَاِنَّهٗ","لَعِلمٌ","لِّلسَّاعَةِ","فَلَا","تَمتَرُنَّ","بِهَا","وَاتَّبِعُونِؕ","هذَا","صِرَاطٌ","مُّستَقِيمٌ"]},"62":{"total_words":8,"words":["وَلَا","يَصُدَّنَّكُمُ","الشَّيطنُ","اِنَّهٗ","لَكُم","عَدُوٌّ","مُّبِينٌ"]},"63":{"total_words":18,"words":["وَ لَمَّا","جَآءَ","عِيسى","بِالبَيِّنتِ","قَالَ","قَد","جِئتُكُم","بِالحِكمَةِ","وَلِاُبَيِّنَ","لَكُم","بَعضَ","الَّذِى","تَختَلِفُونَ","فِيهِ","فَاتَّقُوا","اللّهَ","وَاَطِيعُونِ"]},"64":{"total_words":10,"words":["اِنَّ","اللّهَ","هُوَ","رَبِّى","وَرَبُّكُم","فَاعبُدُوهُؕ","هذَا","صِرَاطٌ","مُّستَقِيمٌ"]},"65":{"total_words":12,"words":["فَاختَلَفَ","الاَحزَابُ","مِن","بَينِهِم","فَوَيلٌ","لِّلَّذِينَ","ظَلَمُوا","مِن","عَذَابِ","يَومٍ","اَلِيمٍ"]},"66":{"total_words":10,"words":["هَل","يَنظُرُونَ","اِلَّا","السَّاعَةَ","اَن","تَاتِيَهُم","بَغتَةً","وَّهُم","لَا","يَشعُرُونَ"]},"67":{"total_words":7,"words":["اَلاَخِلَّاءُ","يَومَٮِٕذٍ","بَعضُهُم","لِبَعضٍ","عَدُوٌّ","اِلَّا","المُتَّقِينَ ؕ"]},"68":{"total_words":8,"words":["يعِبَادِ","لَا","خَوفٌ","عَلَيكُمُ","اليَومَ","وَلَا","اَنتُم","تَحزَنُونَ"]},"69":{"total_words":5,"words":["اَلَّذِينَ","امَنُوا","بِايتِنَا","وَكَانُوا","مُسلِمِينَ"]},"70":{"total_words":5,"words":["اُدخُلُوا","الجَنَّةَ","اَنتُم","وَاَزوَاجُكُم","تُحبَرُونَ"]},"71":{"total_words":17,"words":["يُطَافُ","عَلَيهِم","بِصِحَافٍ","مِّن","ذَهَبٍ","وَّاَكوَابٍ","وَفِيهَا","مَا","تَشتَهِيهِ","الاَنفُسُ","وَتَلَذُّ","الاَعيُنُ","وَاَنتُم","فِيهَا","خلِدُونَ"]},"72":{"total_words":7,"words":["وَتِلكَ","الجَنَّةُ","الَّتِى","اُورِثتُمُوهَا","بِمَا","كُنتُم","تَعمَلُونَ"]},"73":{"total_words":6,"words":["لَكُم","فِيهَا","فَاكِهَةٌ","كَثِيرَةٌ","مِّنهَا","تَاكُلُونَ"]},"74":{"total_words":6,"words":["اِنَّ","المُجرِمِينَ","فِى","عَذَابِ","جَهَنَّمَ","خلِدُونَ"]},"75":{"total_words":6,"words":["لَا","يُفَتَّرُ","عَنهُم","وَهُم","فِيهِ","مُبلِسُونَ"]},"76":{"total_words":6,"words":["وَمَا","ظَلَمنهُم","وَ لكِن","كَانُوا","هُمُ","الظّلِمِينَ"]},"77":{"total_words":9,"words":["وَنَادَوا","يملِكُ","لِيَقضِ","عَلَينَا","رَبُّكَؕ","قَالَ","اِنَّكُم","مّكِثُونَ"]},"78":{"total_words":7,"words":["لَقَد","جِئنكُم","بِالحَقِّ","وَلكِنَّ","اَكثَرَكُم","لِلحَقِّ","كرِهُونَ"]},"79":{"total_words":5,"words":["اَم","اَبرَمُوا","اَمرًا","فَاِنَّا","مُبرِمُونَ"]},"80":{"total_words":12,"words":["اَم","يَحسَبُونَ","اَنَّا","لَا","نَسمَعُ","سِرَّهُم","وَنَجوٮهُمؕ","بَلى","وَرُسُلُنَا","لَدَيهِم","يَكتُبُونَ"]},"81":{"total_words":8,"words":["قُل","اِن","كَانَ","لِلرَّحمنِ","وَلَدٌ","فَاَنَا","اَوَّلُ","العبِدِينَ"]},"82":{"total_words":8,"words":["سُبحنَ","رَبِّ","السَّموتِ","وَالاَرضِ","رَبِّ","العَرشِ","عَمَّا","يَصِفُونَ"]},"83":{"total_words":8,"words":["فَذَرهُم","يَخُوضُوا","وَيَلعَبُوا","حَتّى","يُلقُوا","يَومَهُمُ","الَّذِى","يُوعَدُونَ"]},"84":{"total_words":12,"words":["وَهُوَ","الَّذِى","فِى","السَّمَآءِ","اِلهٌ","وَّفِى","الاَرضِ","اِلهٌ ؕ","وَهُوَ","الحَكِيمُ","العَلِيمُ"]},"85":{"total_words":13,"words":["وَتَبرَكَ","الَّذِى","لَهٗ","مُلكُ","السَّموتِ","وَالاَرضِ","وَمَا","بَينَهُمَا","وَعِندَهٗ","عِلمُ","السَّاعَةِ","وَاِلَيهِ","تُرجَعُونَ"]},"86":{"total_words":13,"words":["وَلَا","يَملِكُ","الَّذِينَ","يَدعُونَ","مِن","دُونِهِ","الشَّفَاعَةَ","اِلَّا","مَن","شَهِدَ","بِالحَقِّ","وَهُم","يَعلَمُونَ"]},"87":{"total_words":9,"words":["وَلَٮِٕن","سَاَلتَهُم","مَّن","خَلَقَهُم","لَيَقُولُنَّ","اللّهُ","فَاَنّى","يُؤفَكُونَ"]},"88":{"total_words":7,"words":["وَقِيلِهٖ","يرَبِّ","اِنَّ","هٓؤُلَاءِ","قَومٌ","لَّا","يُؤمِنُونَ"]},"89":{"total_words":7,"words":["فَاصفَح","عَنهُم","وَقُل","سَلمٌؕ","فَسَوفَ","يَعلَمُونَ"]}}